aws_mage2connector/__init__.py
aws_mage2connector/aws_mage2connector.py
AWS_Mage2Connector-0.0.2.dist-info/LICENSE.txt
AWS_Mage2Connector-0.0.2.dist-info/METADATA
AWS_Mage2Connector-0.0.2.dist-info/WHEEL
AWS_Mage2Connector-0.0.2.dist-info/top_level.txt
AWS_Mage2Connector-0.0.2.dist-info/RECORD
