Metadata-Version: 2.1
Name: AWS-Mage2Connector
Version: 0.0.2
Summary: Use to connect Magento 2.
Home-page: https://github.com/ideabosque/AWS-Mage2Connector
Author: Idea Bosque
Author-email: ideabosque@gmail.com
License: MIT
Download-URL: https://github.com/ideabosque/AWS-Mage2Connector/tarball/0.0.2
Keywords: Magento 2
Platform: any
Classifier: License :: OSI Approved :: MIT License
Classifier: Programming Language :: Python :: 3
Classifier: Programming Language :: Python :: 3.7
Classifier: Environment :: Web Environment
Classifier: Intended Audience :: Developers
Classifier: Operating System :: OS Independent
Classifier: Topic :: Internet :: WWW/HTTP :: Dynamic Content
Classifier: Topic :: Software Development :: Libraries :: Python Modules
Requires-Python: >=3.7
Requires-Dist: requests
Requires-Dist: pymysql
